setup.py
Claypigeon/VERSION
Claypigeon/__init__.py
Claypigeon/filesystem.py
Claypigeon/remote.py
Claypigeon/tests.py
Claypigeon.egg-info/PKG-INFO
Claypigeon.egg-info/SOURCES.txt
Claypigeon.egg-info/dependency_links.txt
Claypigeon.egg-info/entry_points.txt
Claypigeon.egg-info/requires.txt
Claypigeon.egg-info/top_level.txt