Metadata-Version: 1.0
Name: Claypigeon
Version: 0.1.3
Summary: FUSE filesystem for remote ranged HTTP files.
Home-page: https://github.com/openaddresses/claypigeonfs
Author: Michal Migurski
Author-email: mike-pypi@teczno.com
License: UNKNOWN
Platform: UNKNOWN
